{
  "source": "https://micm.gob.do/wp-content/uploads/2026/03/AVISO-PRE.-SEM.CORTE-14-20-de-mar.-DE-2026-5-pesos.pdf",
  "updated_at_utc": "2026-03-13T22:19:11.573883Z",
  "week": {
    "start_date": null,
    "end_date": null
  },
  "currency": "DOP",
  "items": [
    {
      "label": "Gasolina Premium",
      "key": "gasolina_premium",
      "price_dop": 295.1,
      "unit": "galon",
      "change": null
    },
    {
      "label": "Gasolina Regular",
      "key": "gasolina_regular",
      "price_dop": 277.5,
      "unit": "galon",
      "change": null
    },
    {
      "label": "Gasoil Regular",
      "key": "gasoil_regular",
      "price_dop": 229.8,
      "unit": "galon",
      "change": null
    },
    {
      "label": "Gasoil Óptimo",
      "key": "gasoil_optimo",
      "price_dop": 247.1,
      "unit": "galon",
      "change": null
    },
    {
      "label": "Avtur",
      "key": "avtur",
      "price_dop": 67.37,
      "unit": "galon",
      "change": null
    },
    {
      "label": "Kerosene",
      "key": "kerosene",
      "price_dop": 73.2,
      "unit": "galon",
      "change": null
    },
    {
      "label": "Gas Licuado de Petróleo (GLP)",
      "key": "glp",
      "price_dop": 137.2,
      "unit": "galon",
      "change": null
    }
  ]
}